ODTtoText/__init__.py
ODTtoText/odtreader.py
ODTtoText/win32_unicode_argv.py
ODTtoText-0.0.1.dist-info/LICENSE
ODTtoText-0.0.1.dist-info/METADATA
ODTtoText-0.0.1.dist-info/WHEEL
ODTtoText-0.0.1.dist-info/top_level.txt
ODTtoText-0.0.1.dist-info/RECORD
