Metadata-Version: 2.1
Name: ODTtoText
Version: 0.0.1
Summary: ODT files to text in python(3)
Home-page: https://github.com/mr-tafreshi/ODTtoText
Author: Amirmahdi Tafreshi
Author-email: a.tafreshi440@gmail.com
License: GPL
Platform: any
